netyce/__init__.py
netyce/deco_helper.py
netyce/helper.py
netyce/netyce.py
netyce-0.1.15.dist-info/LICENSE
netyce-0.1.15.dist-info/METADATA
netyce-0.1.15.dist-info/WHEEL
netyce-0.1.15.dist-info/top_level.txt
netyce-0.1.15.dist-info/RECORD
