Metadata-Version: 2.1
Name: netyce
Version: 0.1.15
Summary: The NetYCE python library
Home-page: https://www.netyce.com/
Author: Bart Dorlandt
Author-email: bart.dorlandt@netyce.com
License: MIT License
Project-URL: BitBucket Project, https://bitbucket.org/netyce/netyce_python_lib/
Platform: UNKNOWN
Requires-Python: >=3.6
License-File: LICENSE
Requires-Dist: xmltodict
Requires-Dist: PyMySQL
